aurore/__init__.py
aurore/__main__.py
aurore/api.py
aurore/exceptions.py
aurore/git_utils.py
aurore/jsonpointer.py
aurore/proc_rst.py
aurore/proc_xml.py
aurore/selectors.py
aurore/uri_utils.py
aurore/utils2.py
aurore/config/__init__.py
aurore/config/base.py
aurore/config/config_options.py
aurore/config/defaults.py
aurore/utils/__init__.py
aurore/utils/meta.py
aurore/utils/treeutils/__init__.py
aurore/utils/treeutils/lists.py
aurore/utils/treeutils/maps.py
aurore/utils/treeutils/objects.py
aurore/utils/treeutils/paths.py
aurore/utils/treeutils/sets.py
aurore-0.0.9.dist-info/METADATA
aurore-0.0.9.dist-info/WHEEL
aurore-0.0.9.dist-info/entry_points.txt
aurore-0.0.9.dist-info/top_level.txt
aurore-0.0.9.dist-info/RECORD
