Metadata-Version: 2.1
Name: aurore
Version: 0.0.9
Summary: Utilities
Home-page: https://github.com/claudioperez/aurore
Author: Claudio Perez
Author-email: claudio_perez@berkeley.edu
License: UNKNOWN
Platform: UNKNOWN
Classifier: Programming Language :: Python :: 3
Classifier: Operating System :: OS Independent
Requires-Dist: docutils
Requires-Dist: coloredlogs
Requires-Dist: pyyaml
Requires-Dist: jsonpath2
